openbb_charting/__init__.py
openbb_charting/charting.py
openbb_charting/charts/__init__.py
openbb_charting/charts/correlation_matrix.py
openbb_charting/charts/generic_charts.py
openbb_charting/charts/helpers.py
openbb_charting/charts/price_historical.py
openbb_charting/charts/price_performance.py
openbb_charting/charts/relative_rotation.py
openbb_charting/core/__init__.py
openbb_charting/core/assets/Terminal_icon.png
openbb_charting/core/assets/plotly-3.1.0.min.js
openbb_charting/core/backend.py
openbb_charting/core/chart_style.py
openbb_charting/core/config/__init__.py
openbb_charting/core/config/openbb_styles.py
openbb_charting/core/dummy_backend.py
openbb_charting/core/openbb_figure.py
openbb_charting/core/plotly.html
openbb_charting/core/plotly_ta/__init__.py
openbb_charting/core/plotly_ta/base.py
openbb_charting/core/plotly_ta/data_classes.py
openbb_charting/core/plotly_ta/plugins/__init__.py
openbb_charting/core/plotly_ta/plugins/custom_indicators_plugin.py
openbb_charting/core/plotly_ta/plugins/momentum_plugin.py
openbb_charting/core/plotly_ta/plugins/overlap_plugin.py
openbb_charting/core/plotly_ta/plugins/trend_indicators_plugin.py
openbb_charting/core/plotly_ta/plugins/volatility_plugin.py
openbb_charting/core/plotly_ta/plugins/volume_plugin.py
openbb_charting/core/plotly_ta/ta_class.py
openbb_charting/core/plotly_ta/ta_helpers.py
openbb_charting/core/table.html
openbb_charting/core/to_chart.py
openbb_charting/query_params.py
openbb_charting/styles/__init__.py
openbb_charting/styles/colors.py
openbb_charting/styles/default/dark.pltstyle.json
openbb_charting/styles/default/light.pltstyle.json
openbb_charting/styles/default/tables.pltstyle.json
openbb_charting-2.4.1.dist-info/METADATA
openbb_charting-2.4.1.dist-info/WHEEL
openbb_charting-2.4.1.dist-info/entry_points.txt
openbb_charting-2.4.1.dist-info/RECORD
