Metadata-Version: 2.4
Name: openbb-charting
Version: 2.4.1
Summary: Charting extension for OpenBB
License: AGPL-3.0-only
Author: OpenBB Team
Author-email: hello@openbb.co
Requires-Python: >=3.10,<3.14
Classifier: License :: OSI Approved :: GNU Affero General Public License v3
Classifier: Programming Language :: Python :: 3
Classifier: Programming Language :: Python :: 3.10
Classifier: Programming Language :: Python :: 3.11
Classifier: Programming Language :: Python :: 3.12
Classifier: Programming Language :: Python :: 3.13
Provides-Extra: pywry
Requires-Dist: nbformat (>=5.10.0,<6.0.0)
Requires-Dist: openbb-core (>=1.5.7,<2.0.0)
Requires-Dist: pandas-ta-openbb (>=0.4.22,<0.5.0)
Requires-Dist: plotly (>=6.3.1,<7.0.0)
Requires-Dist: pywry (>=0.6.2,<0.7.0) ; extra == "pywry"
